vartrix/__init__.py
vartrix/aliases.py
vartrix/automate.py
vartrix/container.py
vartrix/context.py
vartrix/namespace.py
vartrix/persist.py
vartrix/sequence.py
vartrix/settings.py
vartrix/utils.py
vartrix-0.5.0.dist-info/METADATA
vartrix-0.5.0.dist-info/WHEEL
vartrix-0.5.0.dist-info/licenses/LICENSE
vartrix-0.5.0.dist-info/RECORD
