Metadata-Version: 2.4
Name: vartrix
Version: 0.5.0
Summary: Easily manange and automate variables and parameters.
Project-URL: Homepage, https://github.com/pythoro/vartrix.git
Project-URL: Repository, https://github.com/pythoro/vartrix.git
Project-URL: Documentation, https://vartrix.readthedocs.io/en/latest/
Author-email: Reuben Rusk <pythoro@mindquip.com>
Maintainer-email: Reuben Rusk <pythoro@mindquip.com>
License-Expression: MIT
License-File: LICENSE
Keywords: AUTOMATE,AUTOMATION,PARAMETERS,PARAMETRIC,VARIABLES
Classifier: Development Status :: 3 - Alpha
Classifier: License :: OSI Approved :: MIT License
Classifier: Natural Language :: English
Classifier: Operating System :: OS Independent
Classifier: Programming Language :: Python :: 3
Classifier: Topic :: Software Development :: Libraries :: Python Modules
Requires-Python: ~=3.9
Requires-Dist: numpy>=1.17.2
Requires-Dist: pandas>=0.25.1
Requires-Dist: ruamel-yaml>=0.16.5
